mpyez/__init__.py
mpyez/ezArray.py
mpyez/ezDict.py
mpyez/ezIO.py
mpyez/ezList.py
mpyez/ezMultiprocessing.py
mpyez/ezOS.py
mpyez/ezPlotting.py
mpyez/version.py
mpyez/backend/__init__.py
mpyez/backend/eIO.py
mpyez/backend/eList.py
mpyez/backend/eOS.py
mpyez/backend/ePlotting.py
mpyez/backend/uDict.py
mpyez/backend/uIO.py
mpyez/backend/uList.py
mpyez/backend/uOS.py
mpyez/backend/uPlotting.py
tests/__init__.py
tests/test_list_.py
mpyez-0.1.0.dist-info/LICENSE
mpyez-0.1.0.dist-info/METADATA
mpyez-0.1.0.dist-info/WHEEL
mpyez-0.1.0.dist-info/top_level.txt
mpyez-0.1.0.dist-info/RECORD
