Metadata-Version: 2.1
Name: mpyez
Version: 0.1.0
Summary: Common use utilities for python done easy.
Home-page: https://github.com/syedalimohsinbukhari/mpyez
Author: Syed Ali Mohsin Bukhari
Author-email: syedali.b@outlook.com
License: MIT
Classifier: License :: OSI Approved :: MIT License
Classifier: Programming Language :: Python :: 3.9
Classifier: Programming Language :: Python :: 3.10
Classifier: Programming Language :: Python :: 3.11
Classifier: Programming Language :: Python :: 3.12
Requires-Python: >=3.9
License-File: LICENSE
Requires-Dist: numpy<2.1.0
Requires-Dist: matplotlib
Requires-Dist: setuptools
